tinynn/__init__.py
tinynn/core/__init__.py
tinynn/core/initializer.py
tinynn/core/layer.py
tinynn/core/loss.py
tinynn/core/model.py
tinynn/core/net.py
tinynn/core/optimizer.py
tinynn/utils/__init__.py
tinynn/utils/data_iterator.py
tinynn/utils/dataset.py
tinynn/utils/downloader.py
tinynn/utils/math.py
tinynn/utils/metric.py
tinynn/utils/seeder.py
tinynn/utils/timer.py
tinynn-0.0.4.dist-info/LICENSE
tinynn-0.0.4.dist-info/METADATA
tinynn-0.0.4.dist-info/WHEEL
tinynn-0.0.4.dist-info/top_level.txt
tinynn-0.0.4.dist-info/RECORD
